flytekitplugins_dolt-1.16.12-py3.14-nspkg.pth
flytekitplugins/dolt/__init__.py
flytekitplugins/dolt/schema.py
flytekitplugins_dolt-1.16.12.data/scripts/flytekit_install_dolt.sh
flytekitplugins_dolt-1.16.12.dist-info/METADATA
flytekitplugins_dolt-1.16.12.dist-info/WHEEL
flytekitplugins_dolt-1.16.12.dist-info/namespace_packages.txt
flytekitplugins_dolt-1.16.12.dist-info/top_level.txt
flytekitplugins_dolt-1.16.12.dist-info/RECORD
